bayesiannetwork/__init__.py
bayesiannetwork/network.py
bayesiannetwork/nodes.py
bayesiannnetwork-0.2.dist-info/LICENSE.txt
bayesiannnetwork-0.2.dist-info/METADATA
bayesiannnetwork-0.2.dist-info/WHEEL
bayesiannnetwork-0.2.dist-info/top_level.txt
bayesiannnetwork-0.2.dist-info/RECORD
