Metadata-Version: 2.1
Name: bayesiannnetwork
Version: 0.2
Summary: Paquete para crear redes bayesianas simples
Author: Alejandra Guzmán
Author-email: guzmandominguez.ale@gmail.com
Classifier: Programming Language :: Python :: 3
Classifier: License :: OSI Approved :: MIT License
Classifier: Operating System :: OS Independent
License-File: LICENSE.txt
